koka/__init__.py
koka-0.0.1.dist-info/licenses/LICENSE
koka-0.0.1.dist-info/WHEEL
koka-0.0.1.dist-info/METADATA
koka-0.0.1.dist-info/RECORD
