Metadata-Version: 2.4
Name: koka
Version: 0.0.1
Summary: Algebraic effects for Python - dependency injection and typed error handling inspired by Koka
Keywords: effects,algebraic-effects,dependency-injection,error-handling,koka,functional-programming
Author: HerringtonDarkholme
License-Expression: MIT
License-File: LICENSE
Classifier: Development Status :: 3 - Alpha
Classifier: Intended Audience :: Developers
Classifier: Topic :: Software Development :: Libraries :: Python Modules
Classifier: Programming Language :: Python :: 3
Classifier: Programming Language :: Python :: 3.13
Classifier: Operating System :: OS Independent
Classifier: Typing :: Typed
Requires-Dist: pytest>=7.4.0 ; extra == 'dev'
Requires-Dist: pytest-cov>=4.1.0 ; extra == 'dev'
Requires-Dist: ruff>=0.1.0 ; extra == 'dev'
Requires-Dist: pyright>=1.1.0 ; extra == 'dev'
Requires-Python: >=3.13
Project-URL: Documentation, https://github.com/HerringtonDarkholme/koka#readme
Project-URL: Homepage, https://github.com/HerringtonDarkholme/koka
Project-URL: Issues, https://github.com/HerringtonDarkholme/koka/issues
Project-URL: Repository, https://github.com/HerringtonDarkholme/koka
Provides-Extra: dev
